adoc_link_checker/__init__.py
adoc_link_checker/config.py
adoc_link_checker/cli/__init__.py
adoc_link_checker/cli/commands.py
adoc_link_checker/cli/config.py
adoc_link_checker/cli/logging.py
adoc_link_checker/cli/main.py
adoc_link_checker/cli/types.py
adoc_link_checker/core/__init__.py
adoc_link_checker/core/context.py
adoc_link_checker/core/discovery.py
adoc_link_checker/core/extractor.py
adoc_link_checker/core/processing.py
adoc_link_checker/core/runner.py
adoc_link_checker/http/__init__.py
adoc_link_checker/http/checker.py
adoc_link_checker/http/service.py
adoc_link_checker/reporting/__init__.py
adoc_link_checker/reporting/json.py
adoc_link_checker/utils/__init__.py
adoc_link_checker/utils/exclusions.py
adoc_link_checker/utils/url.py
adoc_link_checker-0.2.1.dist-info/METADATA
adoc_link_checker-0.2.1.dist-info/WHEEL
adoc_link_checker-0.2.1.dist-info/entry_points.txt
adoc_link_checker-0.2.1.dist-info/top_level.txt
adoc_link_checker-0.2.1.dist-info/RECORD
