Metadata-Version: 2.4
Name: adoc-link-checker
Version: 0.2.1
Summary: CLI tool to detect broken HTTP/HTTPS links in AsciiDoc files
Author: Dhrions
License: MIT
Project-URL: Homepage, https://github.com/dhrions/adoc-link-checker
Project-URL: Repository, https://github.com/dhrions/adoc-link-checker
Project-URL: Issues, https://github.com/dhrions/adoc-link-checker/issues
Keywords: asciidoc,links,ci,documentation,antora
Classifier: Development Status :: 4 - Beta
Classifier: Intended Audience :: Developers
Classifier: License :: OSI Approved :: MIT License
Classifier: Programming Language :: Python :: 3
Classifier: Programming Language :: Python :: 3.8
Classifier: Programming Language :: Python :: 3.9
Classifier: Programming Language :: Python :: 3.10
Classifier: Programming Language :: Python :: 3.11
Classifier: Environment :: Console
Classifier: Topic :: Documentation
Classifier: Topic :: Software Development :: Quality Assurance
Requires-Python: >=3.8
Requires-Dist: click>=8.0.0
Requires-Dist: requests>=2.30.0
Requires-Dist: urllib3>=2.0.0
Provides-Extra: dev
Requires-Dist: pytest>=8.0; extra == "dev"
Requires-Dist: pytest-cov; extra == "dev"
Requires-Dist: pytest-mock; extra == "dev"
Requires-Dist: pytest-responses; extra == "dev"
Requires-Dist: responses; extra == "dev"
Requires-Dist: coverage; extra == "dev"
